MANIFEST.in
README
setup.py
example/__init__.py
example/manage.py
example/models.py
example/settings.py
example/tests.py
example/urls.py
example/views.py
modelurl/BeautifulSoup.py
modelurl/__init__.py
modelurl/__init__.pyc
modelurl/importpath.py
modelurl/middleware.py
modelurl/models.py
modelurl/tests.py
modelurl/utils.py
modelurl/redsolution_setup/__init__.py
modelurl/redsolution_setup/admin.py
modelurl/redsolution_setup/make.py
modelurl/redsolution_setup/models.py
modelurl/redsolution_setup/templates/modelurl/redsolutioncms/settings.pyt
redsolutioncms.django_model_url.egg-info/PKG-INFO
redsolutioncms.django_model_url.egg-info/SOURCES.txt
redsolutioncms.django_model_url.egg-info/dependency_links.txt
redsolutioncms.django_model_url.egg-info/entry_points.txt
redsolutioncms.django_model_url.egg-info/not-zip-safe
redsolutioncms.django_model_url.egg-info/requires.txt
redsolutioncms.django_model_url.egg-info/top_level.txt