Metadata-Version: 1.0
Name: redsolutioncms.django-model-url
Version: 0.1.0
Summary: Django model url keeps track your objects' urls and inserts dynamic links in content.
Home-page: UNKNOWN
Author: Alexander Ivanov
Author-email: alexander.ivanov@redsolution.ru
License: LGPL
Keywords: django model url
Platform: UNKNOWN
Classifier: Development Status :: 3 - Alpha
Classifier: Intended Audience :: Developers
Classifier: License :: Freely Distributable
Classifier: Framework :: Django
Classifier: Environment :: Web Environment
Classifier: Natural Language :: Russian
Classifier: Natural Language :: English
Classifier: Operating System :: OS Independent
Classifier: Programming Language :: Python
Classifier: Topic :: Internet :: WWW/HTTP :: Site Management
Classifier: Topic :: Internet :: WWW/HTTP :: Site Management :: Link Checking
